cdk_fargate_run_task/__init__.py
cdk_fargate_run_task/py.typed
cdk_fargate_run_task/_jsii/__init__.py
cdk_fargate_run_task/_jsii/cdk-fargate-run-task@2.0.397.jsii.tgz
cdk_fargate_run_task-2.0.397.dist-info/LICENSE
cdk_fargate_run_task-2.0.397.dist-info/METADATA
cdk_fargate_run_task-2.0.397.dist-info/WHEEL
cdk_fargate_run_task-2.0.397.dist-info/top_level.txt
cdk_fargate_run_task-2.0.397.dist-info/RECORD
